namedtuple_maker/__init__.py
namedtuple_maker/namedtuple_maker.py
namedtuple_maker-1.0.9.dist-info/LICENSE
namedtuple_maker-1.0.9.dist-info/METADATA
namedtuple_maker-1.0.9.dist-info/WHEEL
namedtuple_maker-1.0.9.dist-info/top_level.txt
namedtuple_maker-1.0.9.dist-info/RECORD
