Metadata-Version: 2.1
Name: namedtuple-maker
Version: 1.0.9
Summary: Easily convert iterable objects into `namedtuple` objects.
Home-page: https://github.com/timothyhull/namedtuple-maker
Author: Timothy Hull
Author-email: timothyhull@gmail.com
License: Apache 2.0
Platform: UNKNOWN
Classifier: License :: OSI Approved :: Apache Software License
Classifier: Programming Language :: Python :: 3
Classifier: Programming Language :: Python :: 3.9
License-File: LICENSE
